_jpyinterpreter/__init__.py
_jpyinterpreter/annotations.py
_jpyinterpreter/conversions.py
_jpyinterpreter/jvm_setup.py
_jpyinterpreter/translator.py
blackops_legacy/solver/__init__.py
blackops_legacy/solver/_blackops_java_interop.py
blackops_legacy/solver/_future.py
blackops_legacy/solver/_jpype_type_conversions.py
blackops_legacy/solver/_problem_change.py
blackops_legacy/solver/_solution_manager.py
blackops_legacy/solver/_solver.py
blackops_legacy/solver/_solver_factory.py
blackops_legacy/solver/_solver_manager.py
blackops_legacy/solver/py.typed
blackops_legacy/solver/config/__init__.py
blackops_legacy/solver/config/_config.py
blackops_legacy/solver/config/py.typed
blackops_legacy/solver/domain/__init__.py
blackops_legacy/solver/domain/_annotations.py
blackops_legacy/solver/domain/_types.py
blackops_legacy/solver/domain/_value_range.py
blackops_legacy/solver/domain/_variable_listener.py
blackops_legacy/solver/heuristic/__init__.py
blackops_legacy/solver/heuristic/_nearby_selection.py
blackops_legacy/solver/jars/HdrHistogram-2.2.2.jar
blackops_legacy/solver/jars/LatencyUtils-2.0.3.jar
blackops_legacy/solver/jars/__init__.py
blackops_legacy/solver/jars/angus-activation-2.0.2.jar
blackops_legacy/solver/jars/apiguardian-api-1.1.2.jar
blackops_legacy/solver/jars/asm-9.8.jar
blackops_legacy/solver/jars/asm-analysis-9.8.jar
blackops_legacy/solver/jars/asm-tree-9.8.jar
blackops_legacy/solver/jars/asm-util-9.8.jar
blackops_legacy/solver/jars/assertj-core-3.27.3.jar
blackops_legacy/solver/jars/byte-buddy-1.17.5.jar
blackops_legacy/solver/jars/byte-buddy-agent-1.17.5.jar
blackops_legacy/solver/jars/commons-collections4-4.5.0.jar
blackops_legacy/solver/jars/commons-math3-3.6.1.jar
blackops_legacy/solver/jars/gizmo-1.9.0.jar
blackops_legacy/solver/jars/istack-commons-runtime-4.1.2.jar
blackops_legacy/solver/jars/jakarta.activation-api-2.1.3.jar
blackops_legacy/solver/jars/jakarta.xml.bind-api-4.0.2.jar
blackops_legacy/solver/jars/jandex-3.3.1.jar
blackops_legacy-1.24.0b1.dist-info/licenses/LICENSE.txt
blackops_legacy-1.24.0b1.dist-info/METADATA
blackops_legacy-1.24.0b1.dist-info/WHEEL
blackops_legacy-1.24.0b1.dist-info/top_level.txt
blackops_legacy-1.24.0b1.dist-info/RECORD
