Metadata-Version: 2.4
Name: blackops_legacy
Version: 1.24.0b1
Summary: BlackOps Solver - An AI constraint solver that optimizes planning and scheduling problems
Home-page: https://github.com/blackops-solver/blackops-solver-legacy
License: Apache License Version 2.0
Project-URL: BlackOps Documentation, https://blackops-solver.github.io/
Project-URL: BlackOps Homepage, https://blackops-solver.github.io/
Classifier: Development Status :: 4 - Beta
Classifier: Programming Language :: Python :: 3
Classifier: Topic :: Scientific/Engineering :: Artificial Intelligence
Classifier: Topic :: Software Development :: Libraries :: Java Libraries
Classifier: License :: OSI Approved :: Apache Software License
Classifier: Operating System :: OS Independent
Requires-Python: >=3.10
License-File: LICENSE.txt
Requires-Dist: JPype1==1.5.1
Dynamic: classifier
Dynamic: description
Dynamic: description-content-type
Dynamic: home-page
Dynamic: license
Dynamic: license-file
Dynamic: project-url
Dynamic: requires-dist
Dynamic: requires-python
Dynamic: summary
